regpredict/__init__.py
regpredict/minute_model.pkl
regpredict/minutescaler.gz
regpredict/regbot.py
regpredict/test.py
regpredict/__pycache__/regbot.cpython-310.pyc
regpredict-0.0.69.dist-info/LICENSE
regpredict-0.0.69.dist-info/METADATA
regpredict-0.0.69.dist-info/WHEEL
regpredict-0.0.69.dist-info/top_level.txt
regpredict-0.0.69.dist-info/RECORD
